README.rst
gdprox.py
setup.py
gdprox.egg-info/PKG-INFO
gdprox.egg-info/SOURCES.txt
gdprox.egg-info/dependency_links.txt
gdprox.egg-info/top_level.txt