Metadata-Version: 1.1
Name: gdprox
Version: 0.3
Summary: UNKNOWN
Home-page: http://pypi.python.org/pypi/gdprox
Author: Fabian Pedregosa
Author-email: f@bianp.net
License: BSD
Platform: UNKNOWN
Classifier: Development Status :: 5 - Production/Stable
Classifier: Intended Audience :: Science/Research
Classifier: Intended Audience :: Developers
Classifier: License :: OSI Approved :: BSD License
Classifier: Programming Language :: Python
Classifier: Programming Language :: Python :: 2
Classifier: Programming Language :: Python :: 3
Classifier: Topic :: Software Development
Classifier: Operating System :: POSIX
Classifier: Operating System :: Unix
